{
  "hash": "78f652a130146352d54e296100d0a3aa",
  "result": {
    "engine": "jupyter",
    "markdown": "---\ntitle: \"Top Authors by Year\"\nformat: html\n\n---\n\n<details>\n<summary><strong>1912</strong></summary>\n\n::: {#78a4c7e3 .cell execution_count=1}\n\n::: {.cell-output .cell-output-display}\n![](authors_files/figure-html/cell-2-output-1.png){width=755 height=565}\n:::\n:::\n\n\n</details> \n\n\n<details>\n<summary><strong>1913</strong></summary>\n\n::: {#d83d7efc .cell execution_count=2}\n\n::: {.cell-output .cell-output-display}\n![](authors_files/figure-html/cell-3-output-1.png){width=755 height=565}\n:::\n:::\n\n\n</details> \n\n\n<details>\n<summary><strong>1914</strong></summary>\n\n::: {#25c8aee5 .cell execution_count=3}\n\n::: {.cell-output .cell-output-display}\n![](authors_files/figure-html/cell-4-output-1.png){width=755 height=565}\n:::\n:::\n\n\n</details> \n\n\n<details>\n<summary><strong>1915</strong></summary>\n\n::: {#b7598bf8 .cell execution_count=4}\n\n::: {.cell-output .cell-output-display}\n![](authors_files/figure-html/cell-5-output-1.png){width=755 height=566}\n:::\n:::\n\n\n</details> \n\n\n<details>\n<summary><strong>1916</strong></summary>\n\n::: {#51ef192d .cell execution_count=5}\n\n::: {.cell-output .cell-output-display}\n![](authors_files/figure-html/cell-6-output-1.png){width=758 height=566}\n:::\n:::\n\n\n</details> \n\n\n<details>\n<summary><strong>1917</strong></summary>\n\n::: {#b0081783 .cell execution_count=6}\n\n::: {.cell-output .cell-output-display}\n![](authors_files/figure-html/cell-7-output-1.png){width=755 height=565}\n:::\n:::\n\n\n</details> \n\n\n<details>\n<summary><strong>1918</strong></summary>\n\n::: {#f1db85b1 .cell execution_count=7}\n\n::: {.cell-output .cell-output-display}\n![](authors_files/figure-html/cell-8-output-1.png){width=755 height=565}\n:::\n:::\n\n\n</details> \n\n\n<details>\n<summary><strong>1919</strong></summary>\n\n::: {#751fd122 .cell execution_count=8}\n\n::: {.cell-output .cell-output-display}\n![](authors_files/figure-html/cell-9-output-1.png){width=755 height=565}\n:::\n:::\n\n\n</details> \n\n\n<details>\n<summary><strong>1920</strong></summary>\n\n::: {#0b519937 .cell execution_count=9}\n\n::: {.cell-output .cell-output-display}\n![](authors_files/figure-html/cell-10-output-1.png){width=758 height=565}\n:::\n:::\n\n\n</details> \n\n\n<details>\n<summary><strong>1921</strong></summary>\n\n::: {#5dff0808 .cell execution_count=10}\n\n::: {.cell-output .cell-output-display}\n![](authors_files/figure-html/cell-11-output-1.png){width=754 height=565}\n:::\n:::\n\n\n</details> \n\n\n<details>\n<summary><strong>1922</strong></summary>\n\n::: {#7e202883 .cell execution_count=11}\n\n::: {.cell-output .cell-output-display}\n![](authors_files/figure-html/cell-12-output-1.png){width=755 height=565}\n:::\n:::\n\n\n</details> \n\n",
    "supporting": [
      "authors_files"
    ],
    "filters": [],
    "includes": {}
  }
}